visualtorch/__init__.py
visualtorch/graph.py
visualtorch/layered.py
visualtorch/lenet_style.py
visualtorch/utils/__init__.py
visualtorch/utils/layer_utils.py
visualtorch/utils/utils.py
visualtorch-0.2.4.dist-info/LICENSE
visualtorch-0.2.4.dist-info/METADATA
visualtorch-0.2.4.dist-info/WHEEL
visualtorch-0.2.4.dist-info/top_level.txt
visualtorch-0.2.4.dist-info/RECORD
