Metadata-Version: 2.1
Name: visualtorch
Version: 0.2.4
Summary: Architecture visualization of Torch models
Home-page: https://github.com/willyfh/visualtorch
Author: Willy Fitra Hendria
Author-email: willyfitrahendria@gmail.com
License: MIT
Keywords: visualize architecture,torch visualization,visualtorch
Classifier: Programming Language :: Python :: 3.10
Classifier: Programming Language :: Python :: 3.11
Classifier: Programming Language :: Python :: 3.12
Classifier: License :: OSI Approved :: MIT License
Classifier: Operating System :: OS Independent
Requires-Python: >=3.10
License-File: LICENSE
Requires-Dist: pillow>=10.0.0
Requires-Dist: numpy>=1.18.1
Requires-Dist: aggdraw>=1.3.11
Requires-Dist: torch>=2.0.0
Provides-Extra: dev
Requires-Dist: myst-parser; extra == "dev"
Requires-Dist: nbsphinx; extra == "dev"
Requires-Dist: pandoc; extra == "dev"
Requires-Dist: sphinx<7.0; extra == "dev"
Requires-Dist: sphinx-autodoc-typehints; extra == "dev"
Requires-Dist: sphinx-book-theme; extra == "dev"
Requires-Dist: sphinx-copybutton; extra == "dev"
Requires-Dist: sphinx-design; extra == "dev"
Requires-Dist: sphinx-gallery; extra == "dev"
Requires-Dist: matplotlib; extra == "dev"
Requires-Dist: pre-commit; extra == "dev"
Requires-Dist: pytest; extra == "dev"
